[
  {
    "Id": "0",
    "Name": "Tool to operate and convert NPOI Excel file",
    "DevelopmentStatus": "Stable",
    "Description": "Thank you for your interests in this small tool named NpoiExcel. It is a free tool which enables you to operate, copy, creat, print and convert Excel files while were generated by Npoi. With NpoiExcel, you can create a large range of applications for free. Please feel free to contact *sales@e-iceblue.com* if there is any question while using it.",
    "ReleasedDatge": "0001-01-01T00:00:00",
    "ModifiedDate": "2014-10-23T01:20:27.183-07:00",
    "Files": [
      {
        "Id": "75e871c7-237f-4e83-af68-d507ab39fb9b",
        "FileName": "NPOI_Excel.zip",
        "Url": "./0/75e871c7-237f-4e83-af68-d507ab39fb9b",
        "Type": "Application",
        "UploadDate": "2014-10-23T01:14:27.09-07:00"
      }
    ]
  }
]